langchain_scrapeless/__init__.py
langchain_scrapeless/const.py
langchain_scrapeless/error_messages.py
langchain_scrapeless/py.typed
langchain_scrapeless/tools/__init__.py
langchain_scrapeless/tools/clawer/__init__.py
langchain_scrapeless/tools/clawer/crawl.py
langchain_scrapeless/tools/clawer/scrape.py
langchain_scrapeless/tools/scrapeless_universal_scraping.py
langchain_scrapeless/tools/scraping_api/__init__.py
langchain_scrapeless/tools/scraping_api/google_search.py
langchain_scrapeless/tools/scraping_api/google_trends.py
langchain_scrapeless/utils.py
langchain_scrapeless/wrappers.py
langchain_scrapeless-0.1.3.dist-info/LICENSE
langchain_scrapeless-0.1.3.dist-info/METADATA
langchain_scrapeless-0.1.3.dist-info/WHEEL
langchain_scrapeless-0.1.3.dist-info/RECORD
