Metadata-Version: 2.3
Name: langchain-scrapeless
Version: 0.1.3
Summary: An integration package connecting Scrapeless and LangChain
License: MIT
Keywords: scrapeless,langchain,integration,universal scraping api,scraping,crawl
Author: Scrapeless Team
Author-email: scrapelessteam@gmail.com
Requires-Python: >=3.9,<4.0
Classifier: License :: OSI Approved :: MIT License
Classifier: Programming Language :: Python :: 3
Classifier: Programming Language :: Python :: 3.9
Classifier: Programming Language :: Python :: 3.10
Classifier: Programming Language :: Python :: 3.11
Classifier: Programming Language :: Python :: 3.12
Classifier: Programming Language :: Python :: 3.13
Requires-Dist: jupyter (>=1.1.1,<2.0.0)
Requires-Dist: langchain-core (>=0.3.15,<0.4.0)
Requires-Dist: python-dotenv (>=1.1.1,<2.0.0)
Requires-Dist: scrapeless (==1.1.1)
Project-URL: Issue Tracker, https://github.com/scrapeless-ai/langchain-scrapeless/issues
Project-URL: Repository, https://github.com/scrapeless-ai/langchain-scrapeless
Project-URL: Release Notes, https://github.com/scrapeless-ai/langchain-scrapeless/releases?expanded=true
Project-URL: Scrapeless Homepage, https://scrapeless.com
Project-URL: Source Code, https://github.com/scrapeless-ai/langchain-scrapeless/tree/main
